pyquadim/__init__.py
pyquadim/pyquadim.cpython-37m-x86_64-linux-gnu.so
pyquadim-0.1.1.dist-info/METADATA
pyquadim-0.1.1.dist-info/WHEEL
pyquadim-0.1.1.dist-info/top_level.txt
pyquadim-0.1.1.dist-info/RECORD
