Metadata-Version: 2.1
Name: pyquadim
Version: 0.1.1
Summary: Quadim 到 Python 的简单移植。
Author: Widecss
Author-email: widecss@gmail.com
Project-URL: Documentation, https://github.com/Widecss/wiki/
Project-URL: Code, https://github.com/Widecss/pyquadim/
Project-URL: Issue Tracker, https://github.com/Widecss/pyquadim/issues
Platform: macOS
Platform: Windows
Platform: X11
Requires-Python: >=3.7
